palmsite/__init__.py
palmsite/_embed_impl.py
palmsite/_predict_impl.py
palmsite/cli.py
palmsite/embed_shim.py
palmsite/hf.py
palmsite/infer_simple.py
palmsite/sanitize.py
palmsite-0.2.0.dist-info/licenses/LICENSE
palmsite-0.2.0.dist-info/METADATA
palmsite-0.2.0.dist-info/WHEEL
palmsite-0.2.0.dist-info/entry_points.txt
palmsite-0.2.0.dist-info/top_level.txt
palmsite-0.2.0.dist-info/RECORD
