Metadata-Version: 2.4
Name: palmsite
Version: 0.2.0
Summary: PalmSite: RdRP catalytic center predictor
Author: Ryota Sugimoto
License: Apache-2.0
Requires-Python: >=3.9
License-File: LICENSE
Requires-Dist: click>=8.1
Requires-Dist: numpy>=1.23
Requires-Dist: h5py>=3.10
Requires-Dist: huggingface_hub>=0.24
Requires-Dist: esm==3.1.4
Requires-Dist: torch<3,>=2.2
Dynamic: license-file
